{"users":[{"numberOfWins":27,"psw":"prova","name":"alex","VictoryPoints":243},{"numberOfWins":6,"psw":"prova","name":"ale","VictoryPoints":81},{"numberOfWins":13,"psw":"prova","name":"santa","VictoryPoints":155},{"numberOfWins":"0","psw":"prova","name":"popoio","VictoryPoints":"0"},{"numberOfWins":"0","psw":"prova","name":"puffo","VictoryPoints":"0"},{"numberOfWins":"0","psw":"paperina","name":"paperino","VictoryPoints":"0"},{"numberOfWins":"0","psw":"miriam","name":"gigi","VictoryPoints":"0"},{"numberOfWins":2,"psw":"zita","name":"carlo","VictoryPoints":81},{"numberOfWins":0,"psw":"teocoli","name":"teo","VictoryPoints":0},{"numberOfWins":0,"psw":"1234","name":"1234","VictoryPoints":0},{"numberOfWins":2,"psw":"bbb","name":"aaa","VictoryPoints":9},{"numberOfWins":0,"psw":"aaa","name":"bbb","VictoryPoints":6},{"numberOfWins":2,"psw":"andro","name":"aless","VictoryPoints":9},{"numberOfWins":0,"psw":"ggg","name":"ggg","VictoryPoints":6},{"numberOfWins":0,"psw":"prova","name":"santass","VictoryPoints":6},{"numberOfWins":2,"psw":"ddd","name":"ddd","VictoryPoints":9},{"numberOfWins":0,"psw":"ttt","name":"gggs","VictoryPoints":6},{"numberOfWins":2,"psw":"rrr","name":"rrr","VictoryPoints":9},{"numberOfWins":0,"psw":"yy","name":"yy","VictoryPoints":6},{"numberOfWins":0,"psw":"gty","name":"gty","VictoryPoints":0},{"numberOfWins":0,"psw":"r","name":"wer","VictoryPoints":0}]}